Mopidy_Spotmop-2.4.4.dist-info/METADATA
Mopidy_Spotmop-2.4.4.dist-info/RECORD
Mopidy_Spotmop-2.4.4.dist-info/DESCRIPTION.rst
Mopidy_Spotmop-2.4.4.dist-info/top_level.txt
Mopidy_Spotmop-2.4.4.dist-info/metadata.json
Mopidy_Spotmop-2.4.4.dist-info/WHEEL
Mopidy_Spotmop-2.4.4.dist-info/entry_points.txt
mopidy_spotmop/__init__.py
