Metadata-Version: 2.0
Name: Mopidy-Spotmop
Version: 2.4.4
Summary: A Mopidy Web client that utilizes the Spotify and EchoNest frameworks
Home-page: https://github.com/jaedb/spotmop
Author: James Barnsley
Author-email: james@barnsley.nz
License: GNU General Public License v3 (GPLv3)
Platform: UNKNOWN
Classifier: Environment :: No Input/Output (Daemon)
Classifier: Intended Audience :: End Users/Desktop
Classifier: License :: OSI Approved :: Apache Software License
Classifier: Operating System :: OS Independent
Classifier: Programming Language :: Python :: 2
Classifier: Topic :: Multimedia :: Sound/Audio :: Players
Requires-Dist: setuptools
Requires-Dist: Mopidy (>=0.19)
Requires-Dist: ConfigObj
